poetry_demo_domroon/__init__.py
poetry_demo_domroon-0.1.2.dist-info/WHEEL
poetry_demo_domroon-0.1.2.dist-info/METADATA
poetry_demo_domroon-0.1.2.dist-info/RECORD
