Metadata-Version: 2.1
Name: poetry-demo-domroon
Version: 0.1.2
Summary: Test
Author: Dominik Haeusser
Author-email: haeusser-dominik@web.de
Requires-Python: >=3.10,<4.0
Classifier: Programming Language :: Python :: 3
Classifier: Programming Language :: Python :: 3.10
Requires-Dist: pendulum (>=2.1.2,<3.0.0)
